dumux/common/__init__.py
dumux/common/_common.so
dumux/discretization/__init__.py
dumux-3.4.0.dev20210308.data/data/include/dumux/adaptive/adapt.hh
dumux-3.4.0.dev20210308.data/data/include/dumux/adaptive/griddatatransfer.hh
dumux-3.4.0.dev20210308.data/data/include/dumux/adaptive/initializationindicator.hh
dumux-3.4.0.dev20210308.data/data/include/dumux/adaptive/markelements.hh
dumux-3.4.0.dev20210308.data/data/include/dumux/assembly/boxlocalassembler.hh
dumux-3.4.0.dev20210308.data/data/include/dumux/assembly/boxlocalresidual.hh
dumux-3.4.0.dev20210308.data/data/include/dumux/assembly/cclocalassembler.hh
dumux-3.4.0.dev20210308.data/data/include/dumux/assembly/cclocalresidual.hh
dumux-3.4.0.dev20210308.data/data/include/dumux/assembly/diffmethod.hh
dumux-3.4.0.dev20210308.data/data/include/dumux/assembly/entitycolor.hh
dumux-3.4.0.dev20210308.data/data/include/dumux/assembly/fvassembler.hh
dumux-3.4.0.dev20210308.data/data/include/dumux/assembly/fvlocalassemblerbase.hh
dumux-3.4.0.dev20210308.data/data/include/dumux/assembly/fvlocalresidual.hh
dumux-3.4.0.dev20210308.data/data/include/dumux/assembly/initialsolution.hh
dumux-3.4.0.dev20210308.data/data/include/dumux/assembly/jacobianpattern.hh
dumux-3.4.0.dev20210308.data/data/include/dumux/assembly/numericepsilon.hh
dumux-3.4.0.dev20210308.data/data/include/dumux/assembly/partialreassembler.hh
dumux-3.4.0.dev20210308.data/data/include/dumux/assembly/staggeredfvassembler.hh
dumux-3.4.0.dev20210308.data/data/include/dumux/assembly/staggeredlocalresidual.hh
dumux-3.4.0.dev20210308.data/data/include/dumux/common/balanceequationopts.hh
dumux-3.4.0.dev20210308.data/data/include/dumux/common/boundaryconditions.hh
dumux-3.4.0.dev20210308.data/data/include/dumux/common/boundaryflag.hh
dumux-3.4.0.dev20210308.data/data/include/dumux/common/boundarytypes.hh
dumux-3.4.0.dev20210308.data/data/include/dumux/common/cubicspline.hh
dumux-3.4.0.dev20210308.data/data/include/dumux/common/cubicsplinehermitebasis.hh
dumux-3.4.0.dev20210308.dist-info/COPYING
dumux-3.4.0.dev20210308.dist-info/LICENSE.md
dumux-3.4.0.dev20210308.dist-info/METADATA
dumux-3.4.0.dev20210308.dist-info/WHEEL
dumux-3.4.0.dev20210308.dist-info/top_level.txt
dumux-3.4.0.dev20210308.dist-info/RECORD
