Metadata-Version: 2.1
Name: dumux
Version: 3.4.0.dev20210308
Summary: DuMux is a module for simulation of multi-phase multi-component flow transport in porous media
Home-page: https://dumux.org
Author: The DuMux Team
Author-email: dumux@listserv.uni-stuttgart.de
License: UNKNOWN
Platform: UNKNOWN
Classifier: Programming Language :: C++
Classifier: Programming Language :: Python :: 3
Classifier: License :: OSI Approved :: GNU General Public License (GPL)
Requires-Python: >=3.4
Requires-Dist: dune-common (<=2.8.0.dev20210308)
Requires-Dist: dune-grid (<=2.8.0.dev20210308)
Requires-Dist: dune-localfunctions (<=2.8.0.dev20210308)
Requires-Dist: dune-istl (<=2.8.0.dev20210308)
